wkhtmltopdf/__init__.py
wkhtmltopdf/api.py
wkhtmltopdf/main.py
wkhtmltopdf/tests.py
py3_wkhtmltopdf-0.4.dist-info/AUTHORS.md
py3_wkhtmltopdf-0.4.dist-info/LICENSE
py3_wkhtmltopdf-0.4.dist-info/METADATA
py3_wkhtmltopdf-0.4.dist-info/WHEEL
py3_wkhtmltopdf-0.4.dist-info/top_level.txt
py3_wkhtmltopdf-0.4.dist-info/RECORD
