Metadata-Version: 2.1
Name: py3-wkhtmltopdf
Version: 0.4
Summary: Simple Python 3 wrapper for wkhtmltopdf
Home-page: http://github.com/jontsai/python3-wkhtmltopdf
Author: Jonathan Tsai
Author-email: hello@jontsai.com
License: BSD
Platform: UNKNOWN
Classifier: Programming Language :: Python
Classifier: License :: OSI Approved :: BSD License
Classifier: Development Status :: 4 - Beta
Classifier: Operating System :: OS Independent
Classifier: Intended Audience :: Developers
Classifier: Topic :: Internet :: WWW/HTTP :: Dynamic Content
